{
  "collapse-filter": false,
  "search": "tag:#教资  ",
  "showTags": false,
  "showAttachments": false,
  "hideUnresolved": false,
  "showOrphans": true,
  "collapse-color-groups": false,
  "colorGroups": [],
  "collapse-display": true,
  "showArrow": false,
  "textFadeMultiplier": -0.7,
  "nodeSizeMultiplier": 1.40375569661458,
  "lineSizeMultiplier": 1.99910888671875,
  "collapse-forces": false,
  "centerStrength": 0.278523763020833,
  "repelStrength": 8.93798828125,
  "linkStrength": 0.8170166015625,
  "linkDistance": 203,
  "scale": 0.9891852469568481,
  "close": true
}